co2spectroscopy/__init__.py
co2spectroscopy-0.0.2.dist-info/WHEEL
co2spectroscopy-0.0.2.dist-info/METADATA
co2spectroscopy-0.0.2.dist-info/RECORD
