Metadata-Version: 2.3
Name: co2spectroscopy
Version: 0.0.2
Summary: Process and standardize spectroscopic analyses of CO2 isotopologues
Author-email: mdaeron <mathieu@daeron.fr>
Requires-Python: >= 3.11
